{"pjw": {"Q1": {"user_answer": ["A", "A", "A", "A", "A"], "correct_answer": [{"A": "drit", "B": "real"}, {"A": "ours", "B": "real"}, {"A": "ours", "B": "real"}, {"A": "real", "B": "munit"}, {"A": "real", "B": "munit"}]}, "Q2": {"user_answer": ["A", "A", "A", "A", "A"], "correct_answer": [{"A": "ours", "B": "drit"}, {"A": "drit", "B": "ours"}, {"A": "ours", "B": "drit"}, {"A": "munit", "B": "ours"}, {"A": "munit", "B": "ours"}]}, "Q3": {"user_answer": ["A", "A", "A", "A", "A"], "correct_answer": [{"A": "ours", "B": "drit"}, {"A": "drit", "B": "ours"}, {"A": "ours", "B": "drit"}, {"A": "munit", "B": "ours"}, {"A": "munit", "B": "ours"}]}, "Q4": {"user_answer": ["A", "A", "A", "A", "A"], "correct_answer": [{"A": "ours", "B": "drit"}, {"A": "drit", "B": "ours"}, {"A": "ours", "B": "drit"}, {"A": "munit", "B": "ours"}, {"A": "munit", "B": "ours"}]}}}